[{"arrives_at": "00:06", "carries_packages": false, "departs_at": "00:01", "direction": "0", "has_bike_stands": true, "has_breastfeeding_rooms": false, "has_dining_rooms": false, "is_accessible": false, "train_class": "1131", "train_no": "1298"}, {"arrives_at": "05:50", "carries_packages": false, "departs_at": "05:45", "direction": "0", "has_bike_stands": false, "has_breastfeeding_rooms": false, "has_dining_rooms": false, "is_accessible": false, "train_class": "1131", "train_no": "4138"}, {"arrives_at": "06:14", "carries_packages": false, "departs_at": "06:09", "direction": "0", "has_bike_stands": false, "has_breastfeeding_rooms": false, "has_dining_rooms": false, "is_accessible": false, "train_class": "1131", "train_no": "1112"}, {"arrives_at": "06:33", "carries_packages": false, "departs_at": "06:28", "direction": "0", "has_bike_stands": false, "has_breastfeeding_rooms": false, "has_dining_rooms": false, "is_accessible": false, "train_class": "1131", "train_no": "1120"}, {"arrives_at": "06:52", "carries_packages": false, "departs_at": "06:46", "direction": "0", "has_bike_stands": false, "has_breastfeeding_rooms": false, "has_dining_rooms": false, "is_accessible": false, "train_class": "1131", "train_no": "1122"}, {"arrives_at": "07:10", "carries_packages": false, "departs_at": "07:04", "direction": "0", "has_bike_stands": true, "has_breastfeeding_rooms": false, "has_dining_rooms": false, "is_accessible": false, "train_class": "1131", "train_no": "4148"}, {"arrives_at": "07:19", "carries_packages": false, "departs_at": "07:13", "direction": "0", "has_bike_stands": false, "has_breastfeeding_rooms": false, "has_dining_rooms": false, "is_accessible": false, "train_class": "1131", "train_no": "1128"}, {"arrives_at": "07:28", "carries_packages": false, "departs_at": "07:22", "direction": "0", "has_bike_stands": false, "has_breastfeeding_rooms": false, "has_dining_rooms": false, "is_accessible": false, "train_class": "1131", "train_no": "4152"}, {"arrives_at": "07:37", "carries_packages": false, "departs_at": "07:31", "direction": "0", "has_bike_stands": false, "has_breastfeeding_rooms": false, "has_dining_rooms": false, "is_accessible": false, "train_class": "1131", "train_no": "1132"}, {"arrives_at": "07:43", "carries_packages": false, "departs_at": "07:37", "direction": "0", "has_bike_stands": false, "has_breastfeeding_rooms": false, "has_dining_rooms": false, "is_accessible": false, "train_class": "1131", "train_no": "1130"}, {"arrives_at": "07:51", "carries_packages": false, "departs_at": "07:45", "direction": "0", "has_bike_stands": false, "has_breastfeeding_rooms": false, "has_dining_rooms": false, "is_accessible": false, "train_class": "1131", "train_no": "4154"}, {"arrives_at": "08:08", "carries_packages": false, "departs_at": "08:03", "direction": "0", "has_bike_stands": false, "has_breastfeeding_rooms": false, "has_dining_rooms": false, "is_accessible": false, "train_class": "1131", "train_no": "1134"}, {"arrives_at": "08:22", "carries_packages": false, "departs_at": "08:17", "direction": "0", "has_bike_stands": true, "has_breastfeeding_rooms": false, "has_dining_rooms": false, "is_accessible": false, "train_class": "1131", "train_no": "2114"}, {"arrives_at": "08:32", "carries_packages": false, "departs_at": "08:27", "direction": "0", "has_bike_stands": false, "has_breastfeeding_rooms": false, "has_dining_rooms": false, "is_accessible": false, "train_class": "1131", "train_no": "1136"}, {"arrives_at": "08:53", "carries_packages": false, "departs_at": "08:48", "direction": "0", "has_bike_stands": true, "has_breastfeeding_rooms": false, "has_dining_rooms": false, "is_accessible": false, "train_class": "1131", "train_no": "1138"}, {"arrives_at": "09:14", "carries_packages": false, "departs_at": "09:09", "direction": "0", "has_bike_stands": true, "has_breastfeeding_rooms": false, "has_dining_rooms": false, "is_accessible": false, "train_class": "1131", "train_no": "2116"}, {"arrives_at": "09:27", "carries_packages": false, "departs_at": "09:21", "direction": "0", "has_bike_stands": true, "has_breastfeeding_rooms": false, "has_dining_rooms": false, "is_accessible": false, "train_class": "1131", "train_no": "1148"}, {"arrives_at": "09:49", "carries_packages": false, "departs_at": "09:44", "direction": "0", "has_bike_stands": true, "has_breastfeeding_rooms": false, "has_dining_rooms": false, "is_accessible": false, "train_class": "1131", "train_no": "2124"}, {"arrives_at": "09:57", "carries_packages": false, "departs_at": "09:52", "direction": "0", "has_bike_stands": true, "has_breastfeeding_rooms": false, "has_dining_rooms": false, "is_accessible": false, "train_class": "1131", "train_no": "1152"}, {"arrives_at": "10:10", "carries_packages": false, "departs_at": "10:05", "direction": "0", "has_bike_stands": true, "has_breastfeeding_rooms": false, "has_dining_rooms": false, "is_accessible": false, "train_class": "1131", "train_no": "1158"}, {"arrives_at": "10:26", "carries_packages": false, "departs_at": "10:21", "direction": "0", "has_bike_stands": false, "has_breastfeeding_rooms": false, "has_dining_rooms": false, "is_accessible": false, "train_class": "1131", "train_no": "2134"}, {"arrives_at": "10:52", "carries_packages": false, "departs_at": "10:47", "direction": "0", "has_bike_stands": true, "has_breastfeeding_rooms": false, "has_dining_rooms": false, "is_accessible": false, "train_class": "1131", "train_no": "1162"}, {"arrives_at": "11:10", "carries_packages": false, "departs_at": "11:05", "direction": "0", "has_bike_stands": true, "has_breastfeeding_rooms": false, "has_dining_rooms": false, "is_accessible": false, "train_class": "1131", "train_no": "1168"}, {"arrives_at": "11:35", "carries_packages": false, "departs_at": "11:30", "direction": "0", "has_bike_stands": false, "has_breastfeeding_rooms": false, "has_dining_rooms": false, "is_accessible": false, "train_class": "1131", "train_no": "2144"}, {"arrives_at": "12:04", "carries_packages": false, "departs_at": "11:59", "direction": "0", "has_bike_stands": true, "has_breastfeeding_rooms": false, "has_dining_rooms": false, "is_accessible": false, "train_class": "1131", "train_no": "1172"}, {"arrives_at": "12:19", "carries_packages": false, "departs_at": "12:14", "direction": "0", "has_bike_stands": true, "has_breastfeeding_rooms": false, "has_dining_rooms": false, "is_accessible": false, "train_class": "1131", "train_no": "1178"}, {"arrives_at": "12:31", "carries_packages": false, "departs_at": "12:26", "direction": "0", "has_bike_stands": true, "has_breastfeeding_rooms": false, "has_dining_rooms": false, "is_accessible": false, "train_class": "1131", "train_no": "2154"}, {"arrives_at": "12:57", "carries_packages": false, "departs_at": "12:52", "direction": "0", "has_bike_stands": false, "has_breastfeeding_rooms": false, "has_dining_rooms": false, "is_accessible": false, "train_class": "1131", "train_no": "1182"}, {"arrives_at": "13:10", "carries_packages": false, "departs_at": "13:05", "direction": "0", "has_bike_stands": false, "has_breastfeeding_rooms": false, "has_dining_rooms": false, "is_accessible": false, "train_class": "1131", "train_no": "1188"}, {"arrives_at": "13:31", "carries_packages": false, "departs_at": "13:26", "direction": "0", "has_bike_stands": true, "has_breastfeeding_rooms": false, "has_dining_rooms": false, "is_accessible": false, "train_class": "1131", "train_no": "2164"}, {"arrives_at": "13:59", "carries_packages": false, "departs_at": "13:54", "direction": "0", "has_bike_stands": false, "has_breastfeeding_rooms": false, "has_dining_rooms": false, "is_accessible": false, "train_class": "1131", "train_no": "1192"}, {"arrives_at": "14:10", "carries_packages": false, "departs_at": "14:05", "direction": "0", "has_bike_stands": true, "has_breastfeeding_rooms": false, "has_dining_rooms": false, "is_accessible": false, "train_class": "1131", "train_no": "1198"}, {"arrives_at": "14:31", "carries_packages": false, "departs_at": "14:26", "direction": "0", "has_bike_stands": true, "has_breastfeeding_rooms": false, "has_dining_rooms": false, "is_accessible": false, "train_class": "1131", "train_no": "2174"}, {"arrives_at": "14:53", "carries_packages": false, "departs_at": "14:47", "direction": "0", "has_bike_stands": true, "has_breastfeeding_rooms": false, "has_dining_rooms": false, "is_accessible": false, "train_class": "1131", "train_no": "1202"}, {"arrives_at": "15:10", "carries_packages": false, "departs_at": "15:05", "direction": "0", "has_bike_stands": true, "has_breastfeeding_rooms": false, "has_dining_rooms": false, "is_accessible": false, "train_class": "1131", "train_no": "1208"}, {"arrives_at": "15:35", "carries_packages": false, "departs_at": "15:30", "direction": "0", "has_bike_stands": true, "has_breastfeeding_rooms": false, "has_dining_rooms": false, "is_accessible": false, "train_class": "1131", "train_no": "2184"}, {"arrives_at": "15:59", "carries_packages": false, "departs_at": "15:54", "direction": "0", "has_bike_stands": true, "has_breastfeeding_rooms": false, "has_dining_rooms": false, "is_accessible": false, "train_class": "1131", "train_no": "1218"}, {"arrives_at": "16:08", "carries_packages": false, "departs_at": "16:03", "direction": "0", "has_bike_stands": false, "has_breastfeeding_rooms": false, "has_dining_rooms": false, "is_accessible": false, "train_class": "1131", "train_no": "1212"}, {"arrives_at": "16:31", "carries_packages": false, "departs_at": "16:26", "direction": "0", "has_bike_stands": true, "has_breastfeeding_rooms": false, "has_dining_rooms": false, "is_accessible": false, "train_class": "1131", "train_no": "2194"}, {"arrives_at": "16:55", "carries_packages": false, "departs_at": "16:50", "direction": "0", "has_bike_stands": false, "has_breastfeeding_rooms": false, "has_dining_rooms": false, "is_accessible": false, "train_class": "1131", "train_no": "1222"}, {"arrives_at": "17:12", "carries_packages": false, "departs_at": "17:07", "direction": "0", "has_bike_stands": true, "has_breastfeeding_rooms": false, "has_dining_rooms": false, "is_accessible": false, "train_class": "1131", "train_no": "1228"}, {"arrives_at": "17:27", "carries_packages": false, "departs_at": "17:21", "direction": "0", "has_bike_stands": false, "has_breastfeeding_rooms": false, "has_dining_rooms": false, "is_accessible": false, "train_class": "1131", "train_no": "4232"}, {"arrives_at": "17:43", "carries_packages": false, "departs_at": "17:38", "direction": "0", "has_bike_stands": true, "has_breastfeeding_rooms": false, "has_dining_rooms": false, "is_accessible": false, "train_class": "1131", "train_no": "2204"}, {"arrives_at": "17:50", "carries_packages": false, "departs_at": "17:45", "direction": "0", "has_bike_stands": false, "has_breastfeeding_rooms": false, "has_dining_rooms": false, "is_accessible": false, "train_class": "1131", "train_no": "4234"}, {"arrives_at": "18:03", "carries_packages": false, "departs_at": "17:58", "direction": "0", "has_bike_stands": false, "has_breastfeeding_rooms": false, "has_dining_rooms": false, "is_accessible": false, "train_class": "1131", "train_no": "1232"}, {"arrives_at": "18:23", "carries_packages": false, "departs_at": "18:18", "direction": "0", "has_bike_stands": false, "has_breastfeeding_rooms": false, "has_dining_rooms": false, "is_accessible": false, "train_class": "1131", "train_no": "1238"}, {"arrives_at": "18:42", "carries_packages": false, "departs_at": "18:37", "direction": "0", "has_bike_stands": true, "has_breastfeeding_rooms": false, "has_dining_rooms": false, "is_accessible": false, "train_class": "1131", "train_no": "2214"}, {"arrives_at": "19:04", "carries_packages": false, "departs_at": "18:59", "direction": "0", "has_bike_stands": true, "has_breastfeeding_rooms": false, "has_dining_rooms": false, "is_accessible": false, "train_class": "1131", "train_no": "1242"}, {"arrives_at": "19:09", "carries_packages": false, "departs_at": "19:04", "direction": "0", "has_bike_stands": false, "has_breastfeeding_rooms": false, "has_dining_rooms": false, "is_accessible": false, "train_class": "1131", "train_no": "4240"}, {"arrives_at": "19:19", "carries_packages": false, "departs_at": "19:14", "direction": "0", "has_bike_stands": false, "has_breastfeeding_rooms": false, "has_dining_rooms": false, "is_accessible": false, "train_class": "1131", "train_no": "1248"}, {"arrives_at": "19:39", "carries_packages": false, "departs_at": "19:34", "direction": "0", "has_bike_stands": true, "has_breastfeeding_rooms": false, "has_dining_rooms": false, "is_accessible": false, "train_class": "1131", "train_no": "2224"}, {"arrives_at": "19:56", "carries_packages": false, "departs_at": "19:51", "direction": "0", "has_bike_stands": true, "has_breastfeeding_rooms": false, "has_dining_rooms": false, "is_accessible": false, "train_class": "1131", "train_no": "1252"}, {"arrives_at": "20:07", "carries_packages": false, "departs_at": "20:02", "direction": "0", "has_bike_stands": true, "has_breastfeeding_rooms": false, "has_dining_rooms": false, "is_accessible": false, "train_class": "1131", "train_no": "1258"}, {"arrives_at": "20:30", "carries_packages": false, "departs_at": "20:25", "direction": "0", "has_bike_stands": false, "has_breastfeeding_rooms": false, "has_dining_rooms": false, "is_accessible": false, "train_class": "1131", "train_no": "2234"}, {"arrives_at": "20:45", "carries_packages": false, "departs_at": "20:39", "direction": "0", "has_bike_stands": false, "has_breastfeeding_rooms": false, "has_dining_rooms": false, "is_accessible": false, "train_class": "1131", "train_no": "1262"}, {"arrives_at": "21:14", "carries_packages": false, "departs_at": "21:09", "direction": "0", "has_bike_stands": true, "has_breastfeeding_rooms": false, "has_dining_rooms": false, "is_accessible": false, "train_class": "1131", "train_no": "1268"}, {"arrives_at": "21:28", "carries_packages": false, "departs_at": "21:22", "direction": "0", "has_bike_stands": true, "has_breastfeeding_rooms": false, "has_dining_rooms": false, "is_accessible": false, "train_class": "1131", "train_no": "1272"}, {"arrives_at": "21:51", "carries_packages": false, "departs_at": "21:46", "direction": "0", "has_bike_stands": true, "has_breastfeeding_rooms": false, "has_dining_rooms": false, "is_accessible": false, "train_class": "1131", "train_no": "2244"}, {"arrives_at": "22:09", "carries_packages": false, "departs_at": "22:04", "direction": "0", "has_bike_stands": true, "has_breastfeeding_rooms": false, "has_dining_rooms": false, "is_accessible": false, "train_class": "1131", "train_no": "1278"}, {"arrives_at": "22:24", "carries_packages": false, "departs_at": "22:19", "direction": "0", "has_bike_stands": false, "has_breastfeeding_rooms": false, "has_dining_rooms": false, "is_accessible": false, "train_class": "1131", "train_no": "1280"}, {"arrives_at": "22:39", "carries_packages": false, "departs_at": "22:34", "direction": "0", "has_bike_stands": true, "has_breastfeeding_rooms": false, "has_dining_rooms": false, "is_accessible": false, "train_class": "1131", "train_no": "2254"}, {"arrives_at": "22:52", "carries_packages": false, "departs_at": "22:47", "direction": "0", "has_bike_stands": false, "has_breastfeeding_rooms": false, "has_dining_rooms": false, "is_accessible": false, "train_class": "1131", "train_no": "1282"}, {"arrives_at": "23:27", "carries_packages": false, "departs_at": "23:22", "direction": "0", "has_bike_stands": true, "has_breastfeeding_rooms": false, "has_dining_rooms": false, "is_accessible": false, "train_class": "1131", "train_no": "2264"}]