[{"arrives_at": "08:19", "carries_packages": false, "departs_at": "06:14", "direction": "1", "has_bike_stands": false, "has_breastfeeding_rooms": true, "has_dining_rooms": false, "is_accessible": true, "train_class": "1101", "train_no": "203"}, {"arrives_at": "09:36", "carries_packages": false, "departs_at": "06:21", "direction": "1", "has_bike_stands": false, "has_breastfeeding_rooms": true, "has_dining_rooms": false, "is_accessible": false, "train_class": "1110", "train_no": "605"}, {"arrives_at": "12:28", "carries_packages": false, "departs_at": "09:30", "direction": "1", "has_bike_stands": false, "has_breastfeeding_rooms": true, "has_dining_rooms": false, "is_accessible": false, "train_class": "110D", "train_no": "407"}, {"arrives_at": "13:37", "carries_packages": false, "departs_at": "10:13", "direction": "1", "has_bike_stands": false, "has_breastfeeding_rooms": true, "has_dining_rooms": false, "is_accessible": true, "train_class": "1111", "train_no": "561"}, {"arrives_at": "15:49", "carries_packages": false, "departs_at": "11:43", "direction": "1", "has_bike_stands": true, "has_breastfeeding_rooms": false, "has_dining_rooms": false, "is_accessible": false, "train_class": "1131", "train_no": "4177"}, {"arrives_at": "16:25", "carries_packages": false, "departs_at": "14:10", "direction": "1", "has_bike_stands": false, "has_breastfeeding_rooms": true, "has_dining_rooms": false, "is_accessible": true, "train_class": "1107", "train_no": "223"}, {"arrives_at": "17:46", "carries_packages": false, "departs_at": "15:01", "direction": "1", "has_bike_stands": false, "has_breastfeeding_rooms": true, "has_dining_rooms": false, "is_accessible": true, "train_class": "1108", "train_no": "177"}, {"arrives_at": "19:12", "carries_packages": false, "departs_at": "15:18", "direction": "1", "has_bike_stands": false, "has_breastfeeding_rooms": true, "has_dining_rooms": false, "is_accessible": true, "train_class": "1111", "train_no": "653"}, {"arrives_at": "19:26", "carries_packages": false, "departs_at": "17:01", "direction": "1", "has_bike_stands": false, "has_breastfeeding_rooms": true, "has_dining_rooms": false, "is_accessible": true, "train_class": "1108", "train_no": "181"}, {"arrives_at": "21:43", "carries_packages": false, "departs_at": "18:18", "direction": "1", "has_bike_stands": false, "has_breastfeeding_rooms": true, "has_dining_rooms": false, "is_accessible": false, "train_class": "1110", "train_no": "633"}, {"arrives_at": "22:28", "carries_packages": false, "departs_at": "19:49", "direction": "1", "has_bike_stands": false, "has_breastfeeding_rooms": true, "has_dining_rooms": false, "is_accessible": true, "train_class": "1109", "train_no": "239"}, {"arrives_at": "23:57", "carries_packages": false, "departs_at": "21:11", "direction": "1", "has_bike_stands": false, "has_breastfeeding_rooms": true, "has_dining_rooms": false, "is_accessible": false, "train_class": "110D", "train_no": "251"}]