{"train_no": "248", "has_breastfeeding_rooms": true, "carries_packages": false, "has_dining_rooms": false, "is_accessible": true, "has_bike_stands": false, "train_class": "1107", "stops": [{"station": "1040", "departs_at": "19:01", "arrives_at": "18:58"}, {"station": "1020", "departs_at": "19:09", "arrives_at": "19:08"}, {"station": "1000", "departs_at": "19:20", "arrives_at": "19:17"}, {"station": "0990", "departs_at": "19:27", "arrives_at": "19:26"}, {"station": "0980", "departs_at": "19:31", "arrives_at": "19:30"}, {"station": "7190", "departs_at": "20:31", "arrives_at": "20:29"}, {"station": "7160", "departs_at": "20:39", "arrives_at": "20:37"}, {"station": "7000", "departs_at": "21:32", "arrives_at": "21:30"}]}