{"train_no": "3534", "has_breastfeeding_rooms": false, "carries_packages": false, "has_dining_rooms": false, "is_accessible": false, "has_bike_stands": false, "train_class": "1131", "stops": [{"station": "5120", "departs_at": "17:08", "arrives_at": "17:06"}, {"station": "5110", "departs_at": "17:14", "arrives_at": "17:14"}, {"station": "5100", "departs_at": "17:20", "arrives_at": "17:19"}, {"station": "5090", "departs_at": "17:32", "arrives_at": "17:25"}, {"station": "5080", "departs_at": "17:37", "arrives_at": "17:36"}, {"station": "5070", "departs_at": "17:44", "arrives_at": "17:42"}, {"station": "5060", "departs_at": "17:48", "arrives_at": "17:47"}, {"station": "5050", "departs_at": "17:56", "arrives_at": "17:54"}]}