{"train_no": "3736", "has_breastfeeding_rooms": false, "carries_packages": false, "has_dining_rooms": false, "is_accessible": false, "has_bike_stands": false, "train_class": "1131", "stops": [{"station": "4272", "departs_at": "13:21", "arrives_at": "13:19"}, {"station": "4271", "departs_at": "13:25", "arrives_at": "13:25"}, {"station": "4270", "departs_at": "13:30", "arrives_at": "13:29"}, {"station": "4260", "departs_at": "13:34", "arrives_at": "13:33"}, {"station": "4250", "departs_at": "13:37", "arrives_at": "13:36"}, {"station": "4220", "departs_at": "13:46", "arrives_at": "13:44"}]}