{"train_no": "374", "has_breastfeeding_rooms": true, "carries_packages": false, "has_dining_rooms": false, "is_accessible": true, "has_bike_stands": false, "train_class": "110F", "stops": [{"station": "6000", "departs_at": "16:55", "arrives_at": "16:53"}, {"station": "5230", "departs_at": "17:08", "arrives_at": "17:06"}, {"station": "5220", "departs_at": "17:20", "arrives_at": "17:19"}, {"station": "5190", "departs_at": "17:47", "arrives_at": "17:45"}, {"station": "5120", "departs_at": "18:28", "arrives_at": "18:26"}, {"station": "5050", "departs_at": "18:51", "arrives_at": "18:48"}, {"station": "5000", "departs_at": "19:06", "arrives_at": "19:03"}, {"station": "4440", "departs_at": "19:21", "arrives_at": "19:19"}, {"station": "4400", "departs_at": "19:30", "arrives_at": "19:28"}, {"station": "4340", "departs_at": "19:43", "arrives_at": "19:40"}, {"station": "4220", "departs_at": "20:14", "arrives_at": "20:11"}, {"station": "4120", "departs_at": "20:42", "arrives_at": "20:40"}, {"station": "4080", "departs_at": "21:02", "arrives_at": "20:59"}, {"station": "3470", "departs_at": "21:27", "arrives_at": "21:25"}, {"station": "3390", "departs_at": "21:53", "arrives_at": "21:51"}, {"station": "3360", "departs_at": "22:07", "arrives_at": "22:05"}, {"station": "3300", "departs_at": "22:25", "arrives_at": "22:23"}]}