{"train_no": "3765", "has_breastfeeding_rooms": false, "carries_packages": false, "has_dining_rooms": false, "is_accessible": false, "has_bike_stands": false, "train_class": "1131", "stops": [{"station": "4200", "departs_at": "18:57", "arrives_at": "18:55"}, {"station": "4210", "departs_at": "19:02", "arrives_at": "19:01"}, {"station": "4220", "departs_at": "19:08", "arrives_at": "19:06"}, {"station": "4250", "departs_at": "19:14", "arrives_at": "19:14"}, {"station": "4260", "departs_at": "19:17", "arrives_at": "19:16"}, {"station": "4270", "departs_at": "19:21", "arrives_at": "19:20"}, {"station": "4271", "departs_at": "19:26", "arrives_at": "19:25"}, {"station": "4272", "departs_at": "19:33", "arrives_at": "19:31"}]}