[{"arrives_at": "05:40", "carries_packages": false, "departs_at": "05:25", "direction": "0", "has_bike_stands": true, "has_breastfeeding_rooms": false, "has_dining_rooms": false, "is_accessible": false, "train_class": "1131", "train_no": "2124"}, {"arrives_at": "06:00", "carries_packages": false, "departs_at": "05:45", "direction": "0", "has_bike_stands": false, "has_breastfeeding_rooms": false, "has_dining_rooms": false, "is_accessible": false, "train_class": "1131", "train_no": "2128"}, {"arrives_at": "06:20", "carries_packages": false, "departs_at": "06:05", "direction": "0", "has_bike_stands": false, "has_breastfeeding_rooms": false, "has_dining_rooms": false, "is_accessible": false, "train_class": "1131", "train_no": "2134"}, {"arrives_at": "06:48", "carries_packages": false, "departs_at": "06:33", "direction": "0", "has_bike_stands": true, "has_breastfeeding_rooms": false, "has_dining_rooms": false, "is_accessible": false, "train_class": "1131", "train_no": "2138"}, {"arrives_at": "07:15", "carries_packages": false, "departs_at": "06:56", "direction": "0", "has_bike_stands": false, "has_breastfeeding_rooms": false, "has_dining_rooms": false, "is_accessible": false, "train_class": "1132", "train_no": "2004"}, {"arrives_at": "07:28", "carries_packages": false, "departs_at": "07:13", "direction": "0", "has_bike_stands": false, "has_breastfeeding_rooms": false, "has_dining_rooms": false, "is_accessible": false, "train_class": "1131", "train_no": "2144"}, {"arrives_at": "08:07", "carries_packages": false, "departs_at": "07:52", "direction": "0", "has_bike_stands": true, "has_breastfeeding_rooms": false, "has_dining_rooms": false, "is_accessible": false, "train_class": "1131", "train_no": "3118"}, {"arrives_at": "08:27", "carries_packages": false, "departs_at": "08:12", "direction": "0", "has_bike_stands": true, "has_breastfeeding_rooms": false, "has_dining_rooms": false, "is_accessible": false, "train_class": "1131", "train_no": "2154"}, {"arrives_at": "08:54", "carries_packages": false, "departs_at": "08:39", "direction": "0", "has_bike_stands": true, "has_breastfeeding_rooms": false, "has_dining_rooms": false, "is_accessible": false, "train_class": "1131", "train_no": "3128"}, {"arrives_at": "09:26", "carries_packages": false, "departs_at": "09:05", "direction": "0", "has_bike_stands": true, "has_breastfeeding_rooms": false, "has_dining_rooms": false, "is_accessible": false, "train_class": "1131", "train_no": "2164"}, {"arrives_at": "10:01", "carries_packages": false, "departs_at": "09:38", "direction": "0", "has_bike_stands": false, "has_breastfeeding_rooms": true, "has_dining_rooms": false, "is_accessible": true, "train_class": "1111", "train_no": "506"}, {"arrives_at": "10:07", "carries_packages": false, "departs_at": "09:52", "direction": "0", "has_bike_stands": true, "has_breastfeeding_rooms": false, "has_dining_rooms": false, "is_accessible": false, "train_class": "1131", "train_no": "3138"}, {"arrives_at": "10:31", "carries_packages": false, "departs_at": "10:16", "direction": "0", "has_bike_stands": true, "has_breastfeeding_rooms": false, "has_dining_rooms": false, "is_accessible": false, "train_class": "1131", "train_no": "2174"}, {"arrives_at": "11:06", "carries_packages": false, "departs_at": "10:41", "direction": "0", "has_bike_stands": true, "has_breastfeeding_rooms": false, "has_dining_rooms": false, "is_accessible": false, "train_class": "1131", "train_no": "3148"}, {"arrives_at": "11:31", "carries_packages": false, "departs_at": "11:16", "direction": "0", "has_bike_stands": true, "has_breastfeeding_rooms": false, "has_dining_rooms": false, "is_accessible": false, "train_class": "1131", "train_no": "2184"}, {"arrives_at": "12:07", "carries_packages": false, "departs_at": "11:51", "direction": "0", "has_bike_stands": true, "has_breastfeeding_rooms": false, "has_dining_rooms": false, "is_accessible": false, "train_class": "1131", "train_no": "3158"}, {"arrives_at": "12:31", "carries_packages": false, "departs_at": "12:16", "direction": "0", "has_bike_stands": true, "has_breastfeeding_rooms": false, "has_dining_rooms": false, "is_accessible": false, "train_class": "1131", "train_no": "2194"}, {"arrives_at": "12:51", "carries_packages": false, "departs_at": "12:36", "direction": "0", "has_bike_stands": true, "has_breastfeeding_rooms": false, "has_dining_rooms": false, "is_accessible": false, "train_class": "1131", "train_no": "3168"}, {"arrives_at": "13:31", "carries_packages": false, "departs_at": "13:16", "direction": "0", "has_bike_stands": true, "has_breastfeeding_rooms": false, "has_dining_rooms": false, "is_accessible": false, "train_class": "1131", "train_no": "2204"}, {"arrives_at": "14:05", "carries_packages": false, "departs_at": "13:41", "direction": "0", "has_bike_stands": true, "has_breastfeeding_rooms": false, "has_dining_rooms": false, "is_accessible": false, "train_class": "1131", "train_no": "3178"}, {"arrives_at": "14:20", "carries_packages": false, "departs_at": "14:05", "direction": "0", "has_bike_stands": true, "has_breastfeeding_rooms": false, "has_dining_rooms": false, "is_accessible": false, "train_class": "1131", "train_no": "2214"}, {"arrives_at": "14:52", "carries_packages": false, "departs_at": "14:37", "direction": "0", "has_bike_stands": true, "has_breastfeeding_rooms": false, "has_dining_rooms": false, "is_accessible": false, "train_class": "1131", "train_no": "3188"}, {"arrives_at": "15:17", "carries_packages": false, "departs_at": "15:01", "direction": "0", "has_bike_stands": true, "has_breastfeeding_rooms": false, "has_dining_rooms": false, "is_accessible": false, "train_class": "1131", "train_no": "2224"}, {"arrives_at": "15:56", "carries_packages": false, "departs_at": "15:41", "direction": "0", "has_bike_stands": true, "has_breastfeeding_rooms": false, "has_dining_rooms": false, "is_accessible": false, "train_class": "1131", "train_no": "3198"}, {"arrives_at": "16:13", "carries_packages": false, "departs_at": "15:57", "direction": "0", "has_bike_stands": false, "has_breastfeeding_rooms": false, "has_dining_rooms": false, "is_accessible": false, "train_class": "1131", "train_no": "2234"}, {"arrives_at": "16:32", "carries_packages": false, "departs_at": "16:07", "direction": "0", "has_bike_stands": false, "has_breastfeeding_rooms": true, "has_dining_rooms": false, "is_accessible": true, "train_class": "1111", "train_no": "554"}, {"arrives_at": "16:59", "carries_packages": false, "departs_at": "16:36", "direction": "0", "has_bike_stands": true, "has_breastfeeding_rooms": false, "has_dining_rooms": false, "is_accessible": false, "train_class": "1131", "train_no": "3208"}, {"arrives_at": "17:19", "carries_packages": false, "departs_at": "17:04", "direction": "0", "has_bike_stands": true, "has_breastfeeding_rooms": false, "has_dining_rooms": false, "is_accessible": false, "train_class": "1131", "train_no": "2244"}, {"arrives_at": "17:58", "carries_packages": false, "departs_at": "17:43", "direction": "0", "has_bike_stands": false, "has_breastfeeding_rooms": false, "has_dining_rooms": false, "is_accessible": false, "train_class": "1131", "train_no": "3218"}, {"arrives_at": "18:35", "carries_packages": false, "departs_at": "18:11", "direction": "0", "has_bike_stands": true, "has_breastfeeding_rooms": false, "has_dining_rooms": false, "is_accessible": false, "train_class": "1131", "train_no": "2254"}, {"arrives_at": "19:02", "carries_packages": false, "departs_at": "18:47", "direction": "0", "has_bike_stands": true, "has_breastfeeding_rooms": false, "has_dining_rooms": false, "is_accessible": false, "train_class": "1131", "train_no": "3228"}, {"arrives_at": "19:27", "carries_packages": false, "departs_at": "19:12", "direction": "0", "has_bike_stands": true, "has_breastfeeding_rooms": false, "has_dining_rooms": false, "is_accessible": false, "train_class": "1131", "train_no": "2264"}, {"arrives_at": "19:59", "carries_packages": false, "departs_at": "19:43", "direction": "0", "has_bike_stands": true, "has_breastfeeding_rooms": false, "has_dining_rooms": false, "is_accessible": false, "train_class": "1131", "train_no": "3238"}, {"arrives_at": "20:34", "carries_packages": false, "departs_at": "20:19", "direction": "0", "has_bike_stands": true, "has_breastfeeding_rooms": false, "has_dining_rooms": false, "is_accessible": false, "train_class": "1131", "train_no": "2274"}, {"arrives_at": "21:04", "carries_packages": false, "departs_at": "20:38", "direction": "0", "has_bike_stands": true, "has_breastfeeding_rooms": false, "has_dining_rooms": false, "is_accessible": false, "train_class": "1131", "train_no": "3248"}, {"arrives_at": "21:40", "carries_packages": false, "departs_at": "21:15", "direction": "0", "has_bike_stands": true, "has_breastfeeding_rooms": false, "has_dining_rooms": false, "is_accessible": false, "train_class": "1131", "train_no": "2284"}, {"arrives_at": "21:58", "carries_packages": false, "departs_at": "21:43", "direction": "0", "has_bike_stands": true, "has_breastfeeding_rooms": false, "has_dining_rooms": false, "is_accessible": false, "train_class": "1131", "train_no": "3258"}, {"arrives_at": "22:20", "carries_packages": false, "departs_at": "22:05", "direction": "0", "has_bike_stands": true, "has_breastfeeding_rooms": false, "has_dining_rooms": false, "is_accessible": false, "train_class": "1131", "train_no": "3262"}, {"arrives_at": "22:40", "carries_packages": false, "departs_at": "22:24", "direction": "0", "has_bike_stands": false, "has_breastfeeding_rooms": false, "has_dining_rooms": false, "is_accessible": false, "train_class": "1131", "train_no": "2294"}, {"arrives_at": "22:58", "carries_packages": false, "departs_at": "22:43", "direction": "0", "has_bike_stands": true, "has_breastfeeding_rooms": false, "has_dining_rooms": false, "is_accessible": false, "train_class": "1131", "train_no": "3268"}, {"arrives_at": "23:30", "carries_packages": false, "departs_at": "23:15", "direction": "0", "has_bike_stands": true, "has_breastfeeding_rooms": false, "has_dining_rooms": false, "is_accessible": false, "train_class": "1131", "train_no": "3272"}]