[{"arrives_at": "06:45", "carries_packages": false, "departs_at": "05:49", "direction": "1", "has_bike_stands": true, "has_breastfeeding_rooms": false, "has_dining_rooms": false, "is_accessible": false, "train_class": "1131", "train_no": "1105"}, {"arrives_at": "06:59", "carries_packages": false, "departs_at": "06:18", "direction": "1", "has_bike_stands": false, "has_breastfeeding_rooms": false, "has_dining_rooms": false, "is_accessible": false, "train_class": "1132", "train_no": "2011"}, {"arrives_at": "08:03", "carries_packages": false, "departs_at": "07:02", "direction": "1", "has_bike_stands": true, "has_breastfeeding_rooms": false, "has_dining_rooms": false, "is_accessible": false, "train_class": "1131", "train_no": "2133"}, {"arrives_at": "08:19", "carries_packages": false, "departs_at": "07:25", "direction": "1", "has_bike_stands": true, "has_breastfeeding_rooms": false, "has_dining_rooms": false, "is_accessible": false, "train_class": "1131", "train_no": "1117"}, {"arrives_at": "08:58", "carries_packages": false, "departs_at": "08:03", "direction": "1", "has_bike_stands": true, "has_breastfeeding_rooms": false, "has_dining_rooms": false, "is_accessible": false, "train_class": "1131", "train_no": "2143"}, {"arrives_at": "09:10", "carries_packages": false, "departs_at": "08:13", "direction": "1", "has_bike_stands": false, "has_breastfeeding_rooms": true, "has_dining_rooms": false, "is_accessible": true, "train_class": "1111", "train_no": "507"}, {"arrives_at": "09:23", "carries_packages": false, "departs_at": "08:23", "direction": "1", "has_bike_stands": false, "has_breastfeeding_rooms": false, "has_dining_rooms": false, "is_accessible": false, "train_class": "1131", "train_no": "1127"}, {"arrives_at": "10:08", "carries_packages": false, "departs_at": "09:08", "direction": "1", "has_bike_stands": true, "has_breastfeeding_rooms": false, "has_dining_rooms": false, "is_accessible": false, "train_class": "1131", "train_no": "2153"}, {"arrives_at": "10:32", "carries_packages": false, "departs_at": "09:30", "direction": "1", "has_bike_stands": false, "has_breastfeeding_rooms": false, "has_dining_rooms": false, "is_accessible": false, "train_class": "1131", "train_no": "1137"}, {"arrives_at": "10:57", "carries_packages": false, "departs_at": "10:03", "direction": "1", "has_bike_stands": true, "has_breastfeeding_rooms": false, "has_dining_rooms": false, "is_accessible": false, "train_class": "1131", "train_no": "2163"}, {"arrives_at": "11:01", "carries_packages": false, "departs_at": "10:16", "direction": "1", "has_bike_stands": false, "has_breastfeeding_rooms": true, "has_dining_rooms": false, "is_accessible": false, "train_class": "1110", "train_no": "509"}, {"arrives_at": "11:20", "carries_packages": false, "departs_at": "10:25", "direction": "1", "has_bike_stands": true, "has_breastfeeding_rooms": false, "has_dining_rooms": false, "is_accessible": false, "train_class": "1131", "train_no": "1147"}, {"arrives_at": "11:57", "carries_packages": false, "departs_at": "11:03", "direction": "1", "has_bike_stands": true, "has_breastfeeding_rooms": false, "has_dining_rooms": false, "is_accessible": false, "train_class": "1131", "train_no": "2173"}, {"arrives_at": "12:29", "carries_packages": false, "departs_at": "11:23", "direction": "1", "has_bike_stands": false, "has_breastfeeding_rooms": false, "has_dining_rooms": false, "is_accessible": false, "train_class": "1131", "train_no": "1157"}, {"arrives_at": "12:57", "carries_packages": false, "departs_at": "12:04", "direction": "1", "has_bike_stands": false, "has_breastfeeding_rooms": false, "has_dining_rooms": false, "is_accessible": false, "train_class": "1131", "train_no": "2183"}, {"arrives_at": "13:05", "carries_packages": false, "departs_at": "12:17", "direction": "1", "has_bike_stands": false, "has_breastfeeding_rooms": true, "has_dining_rooms": false, "is_accessible": true, "train_class": "1111", "train_no": "513"}, {"arrives_at": "14:07", "carries_packages": false, "departs_at": "13:06", "direction": "1", "has_bike_stands": false, "has_breastfeeding_rooms": false, "has_dining_rooms": false, "is_accessible": false, "train_class": "1131", "train_no": "2193"}, {"arrives_at": "14:22", "carries_packages": false, "departs_at": "13:26", "direction": "1", "has_bike_stands": false, "has_breastfeeding_rooms": false, "has_dining_rooms": false, "is_accessible": false, "train_class": "1131", "train_no": "1177"}, {"arrives_at": "15:01", "carries_packages": false, "departs_at": "14:08", "direction": "1", "has_bike_stands": true, "has_breastfeeding_rooms": false, "has_dining_rooms": false, "is_accessible": false, "train_class": "1131", "train_no": "2203"}, {"arrives_at": "15:20", "carries_packages": false, "departs_at": "14:25", "direction": "1", "has_bike_stands": false, "has_breastfeeding_rooms": false, "has_dining_rooms": false, "is_accessible": false, "train_class": "1131", "train_no": "1187"}, {"arrives_at": "15:32", "carries_packages": false, "departs_at": "14:40", "direction": "1", "has_bike_stands": false, "has_breastfeeding_rooms": true, "has_dining_rooms": false, "is_accessible": true, "train_class": "1111", "train_no": "561"}, {"arrives_at": "15:57", "carries_packages": false, "departs_at": "15:02", "direction": "1", "has_bike_stands": false, "has_breastfeeding_rooms": false, "has_dining_rooms": false, "is_accessible": false, "train_class": "1131", "train_no": "2213"}, {"arrives_at": "16:21", "carries_packages": false, "departs_at": "15:25", "direction": "1", "has_bike_stands": false, "has_breastfeeding_rooms": false, "has_dining_rooms": false, "is_accessible": false, "train_class": "1131", "train_no": "1197"}, {"arrives_at": "17:14", "carries_packages": false, "departs_at": "16:21", "direction": "1", "has_bike_stands": true, "has_breastfeeding_rooms": false, "has_dining_rooms": false, "is_accessible": false, "train_class": "1131", "train_no": "2223"}, {"arrives_at": "17:32", "carries_packages": false, "departs_at": "16:32", "direction": "1", "has_bike_stands": false, "has_breastfeeding_rooms": false, "has_dining_rooms": false, "is_accessible": false, "train_class": "1131", "train_no": "1207"}, {"arrives_at": "17:57", "carries_packages": false, "departs_at": "17:05", "direction": "1", "has_bike_stands": false, "has_breastfeeding_rooms": true, "has_dining_rooms": false, "is_accessible": false, "train_class": "1110", "train_no": "521"}, {"arrives_at": "18:05", "carries_packages": false, "departs_at": "17:11", "direction": "1", "has_bike_stands": true, "has_breastfeeding_rooms": false, "has_dining_rooms": false, "is_accessible": false, "train_class": "1131", "train_no": "2233"}, {"arrives_at": "18:19", "carries_packages": false, "departs_at": "17:23", "direction": "1", "has_bike_stands": false, "has_breastfeeding_rooms": false, "has_dining_rooms": false, "is_accessible": false, "train_class": "1131", "train_no": "1217"}, {"arrives_at": "19:01", "carries_packages": false, "departs_at": "18:01", "direction": "1", "has_bike_stands": true, "has_breastfeeding_rooms": false, "has_dining_rooms": false, "is_accessible": false, "train_class": "1131", "train_no": "2243"}, {"arrives_at": "19:21", "carries_packages": false, "departs_at": "18:12", "direction": "1", "has_bike_stands": false, "has_breastfeeding_rooms": false, "has_dining_rooms": false, "is_accessible": false, "train_class": "1131", "train_no": "1227"}, {"arrives_at": "19:05", "carries_packages": false, "departs_at": "18:22", "direction": "1", "has_bike_stands": true, "has_breastfeeding_rooms": false, "has_dining_rooms": false, "is_accessible": false, "train_class": "1132", "train_no": "2033"}, {"arrives_at": "19:56", "carries_packages": false, "departs_at": "19:02", "direction": "1", "has_bike_stands": true, "has_breastfeeding_rooms": false, "has_dining_rooms": false, "is_accessible": false, "train_class": "1131", "train_no": "2253"}, {"arrives_at": "20:42", "carries_packages": false, "departs_at": "19:43", "direction": "1", "has_bike_stands": false, "has_breastfeeding_rooms": false, "has_dining_rooms": false, "is_accessible": false, "train_class": "1131", "train_no": "1237"}, {"arrives_at": "20:59", "carries_packages": false, "departs_at": "19:58", "direction": "1", "has_bike_stands": true, "has_breastfeeding_rooms": false, "has_dining_rooms": false, "is_accessible": false, "train_class": "1131", "train_no": "2263"}, {"arrives_at": "21:14", "carries_packages": false, "departs_at": "20:27", "direction": "1", "has_bike_stands": false, "has_breastfeeding_rooms": true, "has_dining_rooms": false, "is_accessible": true, "train_class": "1111", "train_no": "653"}, {"arrives_at": "21:30", "carries_packages": false, "departs_at": "20:32", "direction": "1", "has_bike_stands": false, "has_breastfeeding_rooms": false, "has_dining_rooms": false, "is_accessible": false, "train_class": "1131", "train_no": "1247"}, {"arrives_at": "22:10", "carries_packages": false, "departs_at": "21:16", "direction": "1", "has_bike_stands": true, "has_breastfeeding_rooms": false, "has_dining_rooms": false, "is_accessible": false, "train_class": "1131", "train_no": "2273"}, {"arrives_at": "22:37", "carries_packages": false, "departs_at": "21:35", "direction": "1", "has_bike_stands": false, "has_breastfeeding_rooms": false, "has_dining_rooms": false, "is_accessible": false, "train_class": "1131", "train_no": "1257"}, {"arrives_at": "23:43", "carries_packages": false, "departs_at": "22:51", "direction": "1", "has_bike_stands": false, "has_breastfeeding_rooms": false, "has_dining_rooms": false, "is_accessible": false, "train_class": "1131", "train_no": "1267"}]